<annotation verified="yes">
    <folder>Annotation</folder>
    <filename>frame_290</filename>
    <path>openmv_auto_exposure-PascalVOC-export/Annotations/frame_290.jpg</path>
    <source>
        <database>Unknown</database>
    </source>
    <size>
        <width>320</width>
        <height>240</height>
        <depth>3</depth>
    </size>
    <segmented>0</segmented>
    <object>
    <name>apple</name>
    <pose>Unspecified</pose>
    <truncated>0</truncated>
    <difficult>0</difficult>
    <bndbox>
        <xmin>69.0834216101695</xmin>
        <ymin>116.10540254237289</ymin>
        <xmax>128.2797934322034</xmax>
        <ymax>169.1996159957627</ymax>
    </bndbox>
</object><object>
    <name>hand</name>
    <pose>Unspecified</pose>
    <truncated>0</truncated>
    <difficult>0</difficult>
    <bndbox>
        <xmin>74.51092425847457</xmin>
        <ymin>76.85348252118644</ymin>
        <xmax>233.16452595338984</xmax>
        <ymax>220.5087063029661</ymax>
    </bndbox>
</object>
</annotation>